LICENSE.txt
MANIFEST.in
README.rst
setup.py
mezzanine_references/__init__.py
mezzanine_references/__init__.pyc
mezzanine_references/admin.py
mezzanine_references/admin.pyc
mezzanine_references/models.py
mezzanine_references/models.pyc
mezzanine_references/tests.py
mezzanine_references/views.py
mezzanine_references.egg-info/PKG-INFO
mezzanine_references.egg-info/SOURCES.txt
mezzanine_references.egg-info/dependency_links.txt
mezzanine_references.egg-info/top_level.txt
mezzanine_references/.ropeproject/config.py
mezzanine_references/.ropeproject/globalnames
mezzanine_references/.ropeproject/history
mezzanine_references/.ropeproject/objectdb
mezzanine_references/locale/cs/LC_MESSAGES/django.mo
mezzanine_references/locale/cs/LC_MESSAGES/django.po
mezzanine_references/migrations/0001_initial.py
mezzanine_references/migrations/0002_reference_subtitle.py
mezzanine_references/migrations/__init__.py
mezzanine_references/migrations/__init__.pyc
mezzanine_references/static/css/mezzanine-references.css
mezzanine_references/templates/includes/reference.html
mezzanine_references/templates/pages/references.html
mezzanine_references/templates/references/slideshow.html
mezzanine_references/templatetags/__init__.py
mezzanine_references/templatetags/__init__.pyc
mezzanine_references/templatetags/references_tags.py
mezzanine_references/templatetags/references_tags.pyc
mezzanine_references/templatetags/.ropeproject/config.py
mezzanine_references/templatetags/.ropeproject/globalnames
mezzanine_references/templatetags/.ropeproject/history
mezzanine_references/templatetags/.ropeproject/objectdb