Metadata-Version: 1.1
Name: mezzanine-references
Version: 0.1.5
Summary: 
